dipp/__init__.py
dipp/pytorch/__init__.py
dipp/pytorch/functions.py
dipp/pytorch/modules/__init__.py
dipp/pytorch/modules/generic.py
dipp/pytorch/modules/haarpsi.py
dipp-0.1.0.dev0.dist-info/DESCRIPTION.rst
dipp-0.1.0.dev0.dist-info/METADATA
dipp-0.1.0.dev0.dist-info/RECORD
dipp-0.1.0.dev0.dist-info/WHEEL
dipp-0.1.0.dev0.dist-info/metadata.json
dipp-0.1.0.dev0.dist-info/top_level.txt
