Metadata-Version: 2.0
Name: dipp
Version: 0.1.0.dev0
Summary: **D**eep **I**nverse **P**roblems **P**ackage - a library of add-ons to various Deep Learning frameworks for solving Inverse Problems
Home-page: https://github.com/odlgroup/dipp
Author: Jonas Adler, Holger Kohr
Author-email: odl@math.kth.se
License: MPL-2.0
Keywords: research development mathematics prototyping deep-learning
Platform: UNKNOWN
Provides-Extra: pytorch
Requires-Dist: pytorch; extra == 'pytorch'
Provides-Extra: tensorflow
Requires-Dist: tensorflow; extra == 'tensorflow'
Provides-Extra: testing
Provides-Extra: theano
Requires-Dist: theano; extra == 'theano'
